{
  "fec_id": "C00483693",
  "name": "SIERRA CLUB INDEPENDENT ACTION",
  "fetched_at": "2026-07-23T09:21:20.074958+00:00",
  "totals": [
    {
      "all_loans_received": 0.0,
      "allocated_federal_election_levin_share": 0.0,
      "cash_on_hand_beginning_period": 300727.81,
      "committee_designation": "B",
      "committee_designation_full": "Lobbyist/Registrant PAC",
      "committee_id": "C00483693",
      "committee_name": "SIERRA CLUB INDEPENDENT ACTION",
      "committee_state": "CA",
      "committee_type": "O",
      "committee_type_full": "Super PAC (Independent Expenditure-Only)",
      "contribution_refunds": 0.0,
      "contributions": 73492.0,
      "contributions_ie_and_party_expenditures_made_percent": 0.75,
      "convention_exp": 0.0,
      "coordinated_expenditures_by_party_committee": 0.0,
      "coverage_end_date": "2026-06-30T00:00:00",
      "coverage_start_date": "2025-01-01T00:00:00",
      "cycle": 2026,
      "disbursements": 179851.14,
      "exp_prior_years_subject_limits": 0.0,
      "exp_subject_limits": 0.0,
      "fed_candidate_committee_contributions": 0.0,
      "fed_candidate_contribution_refunds": 0.0,
      "fed_disbursements": 179851.14,
      "fed_election_activity": 0.0,
      "fed_operating_expenditures": 118367.14,
      "fed_receipts": 117792.54,
      "federal_funds": 0.0,
      "filing_frequency": "M",
      "filing_frequency_full": "Monthly filer",
      "first_f1_date": "2010-05-21",
      "first_file_date": "2010-05-21",
      "independent_expenditures": 1340.0,
      "individual_contributions": 63492.0,
      "individual_contributions_percent": 53.9,
      "individual_itemized_contributions": 55234.0,
      "individual_unitemized_contributions": 8258.0,
      "itemized_convention_exp": 0.0,
      "itemized_other_disb": 0.0,
      "itemized_other_income": 0.0,
      "itemized_other_refunds": 0.0,
      "itemized_refunds_relating_convention_exp": 0.0,
      "last_beginning_image_number": "202607179890860902",
      "last_cash_on_hand_end_period": 238669.21,
      "last_debts_owed_by_committee": 0.0,
      "last_debts_owed_to_committee": 0.0,
      "last_report_type_full": "JULY MONTHLY",
      "last_report_year": 2026,
      "loan_repayments_made": 0.0,
      "loan_repayments_received": 0.0,
      "loans_and_loan_repayments_made": 0.0,
      "loans_and_loan_repayments_received": 0.0,
      "loans_made": 0.0,
      "net_contributions": 73492.0,
      "net_operating_expenditures": 74066.6,
      "non_allocated_fed_election_activity": 0.0,
      "offsets_to_operating_expenditures": 44300.54,
      "operating_expenditures": 118367.14,
      "operating_expenditures_percent": 65.81,
      "organization_type": null,
      "organization_type_full": null,
      "other_disbursements": 60144.0,
      "other_fed_operating_expenditures": 118367.14,
      "other_fed_receipts": 0.0,
      "other_political_committee_contributions": 10000.0,
      "other_refunds": 0.0,
      "party_and_other_committee_contributions_percent": 8.49,
      "party_full": null,
      "political_party_committee_contributions": 0.0,
      "receipts": 117792.54,
      "refunded_individual_contributions": 0.0,
      "refunded_other_political_committee_contributions": 0.0,
      "refunded_political_party_committee_contributions": 0.0,
      "refunds_relating_convention_exp": 0.0,
      "shared_fed_activity": 0.0,
      "shared_fed_activity_nonfed": 0.0,
      "shared_fed_operating_expenditures": 0.0,
      "shared_nonfed_operating_expenditures": 0.0,
      "sponsor_candidate_ids": null,
      "sponsor_candidate_list": [],
      "total_exp_subject_limits": 0.0,
      "total_transfers": 0.0,
      "transaction_coverage_date": "2026-05-31",
      "transfers_from_affiliated_party": 0.0,
      "transfers_from_nonfed_account": 0.0,
      "transfers_from_nonfed_levin": 0.0,
      "transfers_to_affiliated_committee": 0.0,
      "treasurer_name": "MELAKU, RAHEL",
      "unitemized_convention_exp": 0.0,
      "unitemized_other_disb": 0.0,
      "unitemized_other_income": 0.0,
      "unitemized_other_refunds": 0.0,
      "unitemized_refunds_relating_convention_exp": 0.0
    }
  ],
  "filings": [
    {
      "additional_bank_names": null,
      "amendment_chain": [
        1998781
      ],
      "amendment_indicator": "N",
      "amendment_version": 0,
      "bank_depository_city": null,
      "bank_depository_name": null,
      "bank_depository_state": null,
      "bank_depository_street_1": null,
      "bank_depository_street_2": null,
      "bank_depository_zip": null,
      "beginning_image_number": "202607179890860902",
      "candidate_id": null,
      "candidate_name": null,
      "cash_on_hand_beginning_period": 238011.92,
      "cash_on_hand_end_period": 238669.21,
      "committee_id": "C00483693",
      "committee_name": "SIERRA CLUB INDEPENDENT ACTION",
      "committee_type": "O",
      "coverage_end_date": "2026-06-30",
      "coverage_start_date": "2026-06-01",
      "csv_url": "https://docquery.fec.gov/csv/781/1998781.csv",
      "cycle": 2026,
      "debts_owed_by_committee": 0.0,
      "debts_owed_to_committee": 0.0,
      "document_description": "JULY MONTHLY 2026",
      "document_type": null,
      "document_type_full": null,
      "election_year": null,
      "ending_image_number": "202607179890860916",
      "fec_file_id": "FEC-1998781",
      "fec_url": "https://docquery.fec.gov/dcdev/posted/1998781.fec",
      "file_number": 1998781,
      "form_category": "REPORT",
      "form_type": "F3X",
      "house_personal_funds": null,
      "html_url": "https://docquery.fec.gov/cgi-bin/forms/C00483693/1998781/",
      "is_amended": false,
      "means_filed": "e-file",
      "most_recent": true,
      "most_recent_file_number": 1998781,
      "net_donations": null,
      "office": null,
      "opposition_personal_funds": null,
      "pages": 15,
      "party": null,
      "pdf_url": "https://docquery.fec.gov/pdf/902/202607179890860902/202607179890860902.pdf",
      "previous_file_number": 1998781,
      "primary_general_indicator": "P",
      "receipt_date": "2026-07-17T00:00:00",
      "report_type": "M7",
      "report_type_full": "JULY MONTHLY",
      "report_year": 2026,
      "request_type": null,
      "senate_personal_funds": null,
      "state": null,
      "sub_id": "4071720261534582092",
      "total_communication_cost": null,
      "total_disbursements": 6.48,
      "total_independent_expenditures": null,
      "total_individual_contributions": null,
      "total_receipts": 663.77,
      "treasurer_name": "MELAKU, RAHEL",
      "update_date": "2026-07-17"
    },
    {
      "additional_bank_names": null,
      "amendment_chain": [
        1982890
      ],
      "amendment_indicator": "N",
      "amendment_version": 0,
      "bank_depository_city": null,
      "bank_depository_name": null,
      "bank_depository_state": null,
      "bank_depository_street_1": null,
      "bank_depository_street_2": null,
      "bank_depository_zip": null,
      "beginning_image_number": "202606129870655959",
      "candidate_id": null,
      "candidate_name": null,
      "cash_on_hand_beginning_period": 268376.2,
      "cash_on_hand_end_period": 238011.92,
      "committee_id": "C00483693",
      "committee_name": "SIERRA CLUB INDEPENDENT ACTION",
      "committee_type": "O",
      "coverage_end_date": "2026-05-31",
      "coverage_start_date": "2026-05-01",
      "csv_url": "https://docquery.fec.gov/csv/890/1982890.csv",
      "cycle": 2026,
      "debts_owed_by_committee": 0.0,
      "debts_owed_to_committee": 0.0,
      "document_description": "JUNE MONTHLY 2026",
      "document_type": null,
      "document_type_full": null,
      "election_year": null,
      "ending_image_number": "202606129870655972",
      "fec_file_id": "FEC-1982890",
      "fec_url": "https://docquery.fec.gov/dcdev/posted/1982890.fec",
      "file_number": 1982890,
      "form_category": "REPORT",
      "form_type": "F3X",
      "house_personal_funds": null,
      "html_url": "https://docquery.fec.gov/cgi-bin/forms/C00483693/1982890/",
      "is_amended": false,
      "means_filed": "e-file",
      "most_recent": true,
      "most_recent_file_number": 1982890,
      "net_donations": null,
      "office": null,
      "opposition_personal_funds": null,
      "pages": 14,
      "party": null,
      "pdf_url": "https://docquery.fec.gov/pdf/959/202606129870655959/202606129870655959.pdf",
      "previous_file_number": 1982890,
      "primary_general_indicator": "P",
      "receipt_date": "2026-06-12T00:00:00",
      "report_type": "M6",
      "report_type_full": "JUNE MONTHLY",
      "report_year": 2026,
      "request_type": null,
      "senate_personal_funds": null,
      "state": null,
      "sub_id": "4061220261521230019",
      "total_communication_cost": null,
      "total_disbursements": 30837.28,
      "total_independent_expenditures": null,
      "total_individual_contributions": null,
      "total_receipts": 473.0,
      "treasurer_name": "MELAKU, RAHEL",
      "update_date": "2026-06-12"
    },
    {
      "additional_bank_names": null,
      "amendment_chain": [
        1975842
      ],
      "amendment_indicator": "N",
      "amendment_version": 0,
      "bank_depository_city": null,
      "bank_depository_name": null,
      "bank_depository_state": null,
      "bank_depository_street_1": null,
      "bank_depository_street_2": null,
      "bank_depository_zip": null,
      "beginning_image_number": "202605189866981044",
      "candidate_id": null,
      "candidate_name": null,
      "cash_on_hand_beginning_period": 257903.86,
      "cash_on_hand_end_period": 268376.2,
      "committee_id": "C00483693",
      "committee_name": "SIERRA CLUB INDEPENDENT ACTION",
      "committee_type": "O",
      "coverage_end_date": "2026-04-30",
      "coverage_start_date": "2026-04-01",
      "csv_url": "https://docquery.fec.gov/csv/842/1975842.csv",
      "cycle": 2026,
      "debts_owed_by_committee": 0.0,
      "debts_owed_to_committee": 0.0,
      "document_description": "MAY MONTHLY 2026",
      "document_type": null,
      "document_type_full": null,
      "election_year": null,
      "ending_image_number": "202605189866981068",
      "fec_file_id": "FEC-1975842",
      "fec_url": "https://docquery.fec.gov/dcdev/posted/1975842.fec",
      "file_number": 1975842,
      "form_category": "REPORT",
      "form_type": "F3X",
      "house_personal_funds": null,
      "html_url": "https://docquery.fec.gov/cgi-bin/forms/C00483693/1975842/",
      "is_amended": false,
      "means_filed": "e-file",
      "most_recent": true,
      "most_recent_file_number": 1975842,
      "net_donations": null,
      "office": null,
      "opposition_personal_funds": null,
      "pages": 25,
      "party": null,
      "pdf_url": "https://docquery.fec.gov/pdf/044/202605189866981044/202605189866981044.pdf",
      "previous_file_number": 1975842,
      "primary_general_indicator": "P",
      "receipt_date": "2026-05-18T00:00:00",
      "report_type": "M5",
      "report_type_full": "MAY MONTHLY",
      "report_year": 2026,
      "request_type": null,
      "senate_personal_funds": null,
      "state": null,
      "sub_id": "4051820261510512066",
      "total_communication_cost": null,
      "total_disbursements": 30.66,
      "total_independent_expenditures": null,
      "total_individual_contributions": null,
      "total_receipts": 10503.0,
      "treasurer_name": "MELAKU, RAHEL",
      "update_date": "2026-05-18"
    },
    {
      "additional_bank_names": null,
      "amendment_chain": [
        1967946
      ],
      "amendment_indicator": "N",
      "amendment_version": 0,
      "bank_depository_city": null,
      "bank_depository_name": null,
      "bank_depository_state": null,
      "bank_depository_street_1": null,
      "bank_depository_street_2": null,
      "bank_depository_zip": null,
      "beginning_image_number": "202604169863132172",
      "candidate_id": null,
      "candidate_name": null,
      "cash_on_hand_beginning_period": 257315.79,
      "cash_on_hand_end_period": 257903.86,
      "committee_id": "C00483693",
      "committee_name": "SIERRA CLUB INDEPENDENT ACTION",
      "committee_type": "O",
      "coverage_end_date": "2026-03-31",
      "coverage_start_date": "2026-03-01",
      "csv_url": "https://docquery.fec.gov/csv/946/1967946.csv",
      "cycle": 2026,
      "debts_owed_by_committee": 0.0,
      "debts_owed_to_committee": 0.0,
      "document_description": "APRIL MONTHLY 2026",
      "document_type": null,
      "document_type_full": null,
      "election_year": null,
      "ending_image_number": "202604169863132192",
      "fec_file_id": "FEC-1967946",
      "fec_url": "https://docquery.fec.gov/dcdev/posted/1967946.fec",
      "file_number": 1967946,
      "form_category": "REPORT",
      "form_type": "F3X",
      "house_personal_funds": null,
      "html_url": "https://docquery.fec.gov/cgi-bin/forms/C00483693/1967946/",
      "is_amended": false,
      "means_filed": "e-file",
      "most_recent": true,
      "most_recent_file_number": 1967946,
      "net_donations": null,
      "office": null,
      "opposition_personal_funds": null,
      "pages": 21,
      "party": null,
      "pdf_url": "https://docquery.fec.gov/pdf/172/202604169863132172/202604169863132172.pdf",
      "previous_file_number": 1967946,
      "primary_general_indicator": "P",
      "receipt_date": "2026-04-16T00:00:00",
      "report_type": "M4",
      "report_type_full": "APRIL MONTHLY",
      "report_year": 2026,
      "request_type": null,
      "senate_personal_funds": null,
      "state": null,
      "sub_id": "4041620261435909550",
      "total_communication_cost": null,
      "total_disbursements": 24.93,
      "total_independent_expenditures": null,
      "total_individual_contributions": null,
      "total_receipts": 613.0,
      "treasurer_name": "MELAKU, RAHEL",
      "update_date": "2026-04-16"
    },
    {
      "additional_bank_names": null,
      "amendment_chain": [
        1953306
      ],
      "amendment_indicator": "N",
      "amendment_version": 0,
      "bank_depository_city": null,
      "bank_depository_name": null,
      "bank_depository_state": null,
      "bank_depository_street_1": null,
      "bank_depository_street_2": null,
      "bank_depository_zip": null,
      "beginning_image_number": "202603169853389561",
      "candidate_id": null,
      "candidate_name": null,
      "cash_on_hand_beginning_period": 256880.97,
      "cash_on_hand_end_period": 257315.79,
      "committee_id": "C00483693",
      "committee_name": "SIERRA CLUB INDEPENDENT ACTION",
      "committee_type": "O",
      "coverage_end_date": "2026-02-28",
      "coverage_start_date": "2026-02-01",
      "csv_url": "https://docquery.fec.gov/csv/306/1953306.csv",
      "cycle": 2026,
      "debts_owed_by_committee": 0.0,
      "debts_owed_to_committee": 0.0,
      "document_description": "MARCH MONTHLY 2026",
      "document_type": null,
      "document_type_full": null,
      "election_year": null,
      "ending_image_number": "202603169853389572",
      "fec_file_id": "FEC-1953306",
      "fec_url": "https://docquery.fec.gov/dcdev/posted/1953306.fec",
      "file_number": 1953306,
      "form_category": "REPORT",
      "form_type": "F3X",
      "house_personal_funds": null,
      "html_url": "https://docquery.fec.gov/cgi-bin/forms/C00483693/1953306/",
      "is_amended": false,
      "means_filed": "e-file",
      "most_recent": true,
      "most_recent_file_number": 1953306,
      "net_donations": null,
      "office": null,
      "opposition_personal_funds": null,
      "pages": 12,
      "party": null,
      "pdf_url": "https://docquery.fec.gov/pdf/561/202603169853389561/202603169853389561.pdf",
      "previous_file_number": 1953306,
      "primary_general_indicator": "P",
      "receipt_date": "2026-03-16T00:00:00",
      "report_type": "M3",
      "report_type_full": "MARCH MONTHLY",
      "report_year": 2026,
      "request_type": null,
      "senate_personal_funds": null,
      "state": null,
      "sub_id": "4031620261423446018",
      "total_communication_cost": null,
      "total_disbursements": 93.18,
      "total_independent_expenditures": null,
      "total_individual_contributions": null,
      "total_receipts": 528.0,
      "treasurer_name": "MELAKU, RAHEL",
      "update_date": "2026-03-16"
    }
  ]
}