{
  "fec_id": "H8OH12230",
  "name": "LETT, CRYSTAL LYNN",
  "fetched_at": "2026-07-24T09:16:06.806619+00:00",
  "totals": [],
  "filings": [
    {
      "additional_bank_names": null,
      "amendment_chain": [
        1197074
      ],
      "amendment_indicator": "N",
      "amendment_version": 0,
      "bank_depository_city": null,
      "bank_depository_name": null,
      "bank_depository_state": null,
      "bank_depository_street_1": null,
      "bank_depository_street_2": null,
      "bank_depository_zip": null,
      "beginning_image_number": "201801129090397873",
      "candidate_id": "H8OH12230",
      "candidate_name": "LETT, CRYSTAL LYNN",
      "cash_on_hand_beginning_period": null,
      "cash_on_hand_end_period": null,
      "committee_id": "H8OH12230",
      "committee_name": null,
      "committee_type": null,
      "coverage_end_date": null,
      "coverage_start_date": null,
      "csv_url": "https://docquery.fec.gov/csv/074/1197074.csv",
      "cycle": 2018,
      "debts_owed_by_committee": null,
      "debts_owed_to_committee": null,
      "document_description": "Statement of Candidacy 2018",
      "document_type": null,
      "document_type_full": null,
      "election_year": 2018,
      "ending_image_number": "201801129090397873",
      "fec_file_id": "FEC-1197074",
      "fec_url": "https://docquery.fec.gov/dcdev/posted/1197074.fec",
      "file_number": 1197074,
      "form_category": "STATEMENT",
      "form_type": "F2",
      "house_personal_funds": null,
      "html_url": "https://docquery.fec.gov/cgi-bin/forms/H8OH12230/1197074/",
      "is_amended": false,
      "means_filed": "e-file",
      "most_recent": true,
      "most_recent_file_number": 1197074,
      "net_donations": null,
      "office": "H",
      "opposition_personal_funds": null,
      "pages": 1,
      "party": "DEM",
      "pdf_url": "https://docquery.fec.gov/pdf/873/201801129090397873/201801129090397873.pdf",
      "previous_file_number": 1197074,
      "primary_general_indicator": null,
      "receipt_date": "2018-01-12T00:00:00",
      "report_type": null,
      "report_type_full": null,
      "report_year": 2018,
      "request_type": null,
      "senate_personal_funds": null,
      "state": "OH",
      "sub_id": "4011220181502831548",
      "total_communication_cost": null,
      "total_disbursements": null,
      "total_independent_expenditures": null,
      "total_individual_contributions": null,
      "total_receipts": null,
      "treasurer_name": "LETT, CRYSTAL LYNN",
      "update_date": "2018-01-12"
    }
  ]
}